hogwarts_playwright_agent-0.2.3-py3-none-any.whl
hogwarts_ai_agent/__init__.py
hogwarts_ai_agent/__main__.py
hogwarts_ai_agent/model/__init__.py
hogwarts_ai_agent/model/llm_model.py
hogwarts_ai_agent/model/mcp_model.py
hogwarts_ai_agent/model/settings.py
hogwarts_ai_agent/model/web_model.py
hogwarts_ai_agent/pyarmor_runtime_000000/__init__.py
hogwarts_ai_agent/pyarmor_runtime_000000/darwin_universal/pyarmor_runtime.so
hogwarts_ai_agent/pyarmor_runtime_000000/linux_aarch64/pyarmor_runtime.so
hogwarts_ai_agent/pyarmor_runtime_000000/linux_x86_64/pyarmor_runtime.so
hogwarts_ai_agent/pyarmor_runtime_000000/windows_x86_64/pyarmor_runtime.pyd
hogwarts_ai_agent/service/__init__.py
hogwarts_ai_agent/service/llm_node.py
hogwarts_ai_agent/service/log.py
hogwarts_ai_agent/service/mcp_node.py
hogwarts_ai_agent/service/mcp_register.py
hogwarts_ai_agent/service/mcp_server.py
hogwarts_ai_agent/service/workflow.py
hogwarts_ai_agent/tests/__init__.py
hogwarts_ai_agent/tests/test_anggraph_oop_agent.py
hogwarts_playwright_agent-0.2.3.dist-info/METADATA
hogwarts_playwright_agent-0.2.3.dist-info/RECORD.bak
hogwarts_playwright_agent-0.2.3.dist-info/WHEEL
hogwarts_playwright_agent-0.2.3.dist-info/entry_points.txt
hogwarts_playwright_agent-0.2.3.dist-info/top_level.txt
hogwarts_playwright_agent-0.2.3.dist-info/RECORD
